odoo/addons/role_policy_hr/README.rst
odoo/addons/role_policy_hr/__init__.py
odoo/addons/role_policy_hr/__manifest__.py
odoo/addons/role_policy_hr/i18n/role_policy_hr.pot
odoo/addons/role_policy_hr/models/__init__.py
odoo/addons/role_policy_hr/models/base.py
odoo/addons/role_policy_hr/readme/CONTRIBUTORS.rst
odoo/addons/role_policy_hr/readme/DESCRIPTION.rst
odoo/addons/role_policy_hr/static/description/icon.png
odoo/addons/role_policy_hr/static/description/index.html
odoo/addons/role_policy_hr/static/src/js/role_policy_hr.js
odoo/addons/role_policy_hr/views/assets_backend.xml
odoo13_addon_role_policy_hr-13.0.1.1.0.dist-info/METADATA
odoo13_addon_role_policy_hr-13.0.1.1.0.dist-info/WHEEL
odoo13_addon_role_policy_hr-13.0.1.1.0.dist-info/top_level.txt
odoo13_addon_role_policy_hr-13.0.1.1.0.dist-info/RECORD
